
{
  "week": 3,
  "path": "alphabet",
  "targetLanguage": "Italian",
  "nativeLanguage": "Urdu",
  "days": [
    {
      "week": 3,
      "day": 15,
      "letter": "Q",
      "title": "Day 15: Letter Q",
      "title_native": "پندرہواں دن: حرف Q",
      "theme": "Consonants",
      "path": "alphabet",
      "targetLanguage": "Italian",
      "nativeLanguage": "Urdu",
      "words": [
        {
          "id": "ui_q_1",
          "target": "Quadro",
          "phonetic": "کوآدرو",
          "native_meaning": "تصویر / پینٹنگ",
          "english": "Painting",
          "example_sentence_target": "Il quadro è antico.",
          "example_sentence_native": "پینٹنگ قدیم ہے۔",
          "example_sentence_phonetic": "اِل کوآدرو اے انتیکو۔"
        }
      ],
      "exercises": {
        "writingPractice": [{ "id": "w_ui_q", "letter": "Q", "hint": "Q لکھیں" }],
        "multipleChoice": [{ "id": "mc_ui_q", "question": "حرف 'Q' کے بعد ہمیشہ کون سا حرف آتا ہے؟", "options": ["A", "I", "U", "E"], "correct": 2, "explanation": "اطالوی میں 'Q' کے بعد ہمیشہ 'U' آتا ہے۔" }]
      },
      "cultural_note": "اٹلی دنیا بھر میں اپنی آرٹ گیلریوں اور پینٹنگز کے لیے مشہور ہے۔",
      "pronunciation_tip": "'Q' کا نام 'کُو' (Qu) ہے اور اسے ہمیشہ 'U' کے ساتھ ملا کر 'کو' بولا جاتا ہے۔",
      "progress": { "xp": 50, "streak_bonus": 10, "badge": "IT-Q" }
    },
    {
      "week": 3,
      "day": 16,
      "letter": "R",
      "title": "Day 16: Letter R",
      "title_native": "سولہواں دن: حرف R",
      "theme": "Rolling Sounds",
      "path": "alphabet",
      "targetLanguage": "Italian",
      "nativeLanguage": "Urdu",
      "words": [
        {
          "id": "ui_r_1",
          "target": "Rosa",
          "phonetic": "روزہ",
          "native_meaning": "گلاب",
          "english": "Rose",
          "example_sentence_target": "La rosa profuma.",
          "example_sentence_native": "گلاب خوشبو دیتا ہے۔",
          "example_sentence_phonetic": "لا روزہ پروفوما۔"
        }
      ],
      "exercises": {
        "writingPractice": [{ "id": "w_ui_r", "letter": "R", "hint": "R لکھیں" }],
        "matching": [{ "id": "m_ui_r", "target": "Rosa", "native": "گلاب" }]
      },
      "cultural_note": "اٹلی میں 'Giro d'Italia' نامی سائیکل ریس میں جیتنے والا 'گلابی' جرسی پہنتا ہے۔",
      "pronunciation_tip": "'R' کی آواز اردو کے 'ر' جیسی ہے لیکن اسے زبان کی نوک سے تھوڑا 'رول' (Roll) کیا جاتا ہے۔",
      "progress": { "xp": 50, "streak_bonus": 10, "badge": "IT-R" }
    },
    {
      "week": 3,
      "day": 17,
      "letter": "S",
      "title": "Day 17: Letter S",
      "title_native": "سترہواں دن: حرف S",
      "theme": "Consonants",
      "path": "alphabet",
      "targetLanguage": "Italian",
      "nativeLanguage": "Urdu",
      "words": [
        {
          "id": "ui_s_1",
          "target": "Sole",
          "phonetic": "سولے",
          "native_meaning": "سورج",
          "english": "Sun",
          "example_sentence_target": "C'è il sole.",
          "example_sentence_native": "سورج نکلا ہوا ہے۔",
          "example_sentence_phonetic": "چلے اِل سولے۔"
        }
      ],
      "exercises": {
        "writingPractice": [{ "id": "w_ui_s", "letter": "S", "hint": "S لکھیں" }],
        "fillBlanks": [{ "id": "f_ui_s", "sentence": "C'è il ___.", "answer": "sole", "hint": "سورج (Sun)" }]
      },
      "cultural_note": "اٹلی کو 'ملکِ آفتاب' بھی کہا جاتا ہے کیونکہ وہاں دھوپ بہت ہوتی ہے۔",
      "pronunciation_tip": "'S' کا نام 'ایسّے' (Esse) ہے اور آواز 'س' یا 'ز' کی ہو سکتی ہے۔",
      "progress": { "xp": 50, "streak_bonus": 10, "badge": "IT-S" }
    },
    {
      "week": 3,
      "day": 18,
      "letter": "T",
      "title": "Day 18: Letter T",
      "title_native": "اٹھارہواں دن: حرف T",
      "theme": "Consonants",
      "path": "alphabet",
      "targetLanguage": "Italian",
      "nativeLanguage": "Urdu",
      "words": [
        {
          "id": "ui_t_1",
          "target": "Treno",
          "phonetic": "ترینوں",
          "native_meaning": "ٹرین",
          "english": "Train",
          "example_sentence_target": "Il treno è veloce.",
          "example_sentence_native": "ٹرین تیز ہے۔",
          "example_sentence_phonetic": "اِل ترینوں اے ویلوچے۔"
        }
      ],
      "exercises": {
        "writingPractice": [{ "id": "w_ui_t", "letter": "T", "hint": "T لکھیں" }],
        "matching": [{ "id": "m_ui_t", "target": "Treno", "native": "ٹرین" }]
      },
      "cultural_note": "اٹلی کا ریلوے نظام یورپ کے بہترین نظاموں میں سے ایک ہے۔",
      "pronunciation_tip": "اطالوی 'T' اردو کے 'ت' کی طرح نرم ہوتا ہے، انگریزی کے 'ٹ' کی طرح سخت نہیں۔",
      "progress": { "xp": 50, "streak_bonus": 10, "badge": "IT-T" }
    },
    {
      "week": 3,
      "day": 19,
      "letter": "U",
      "title": "Day 19: Letter U",
      "title_native": "انیسواں دن: حرف U",
      "theme": "Vowels",
      "path": "alphabet",
      "targetLanguage": "Italian",
      "nativeLanguage": "Urdu",
      "words": [
        {
          "id": "ui_u_1",
          "target": "Uovo",
          "phonetic": "اووو",
          "native_meaning": "انڈا",
          "english": "Egg",
          "example_sentence_target": "Mangio un uovo.",
          "example_sentence_native": "میں انڈا کھاتا ہوں۔",
          "example_sentence_phonetic": "مانجیو اُن اووو۔"
        }
      ],
      "exercises": {
        "writingPractice": [{ "id": "w_ui_u", "letter": "U", "hint": "U لکھیں" }],
        "sentenceScramble": [{ "id": "s_ui_u", "scrambled": ["un", "uovo", "Mangio"], "correct": "Mangio un uovo", "nativeHint": "میں انڈا کھاتا ہوں۔" }]
      },
      "cultural_note": "ایسٹر کے موقع پر اٹلی میں چاکلیٹ کے بڑے انڈے (Uova di Pasqua) تحفے میں دیے جاتے ہیں۔",
      "pronunciation_tip": "'U' کی آواز اردو کے 'او' (Oo) جیسی ہوتی ہے۔",
      "progress": { "xp": 50, "streak_bonus": 10, "badge": "IT-U" }
    },
    {
      "week": 3,
      "day": 20,
      "letter": "V",
      "title": "Day 20: Letter V",
      "title_native": "بیسواں دن: حرف V",
      "theme": "Consonants",
      "path": "alphabet",
      "targetLanguage": "Italian",
      "nativeLanguage": "Urdu",
      "words": [
        {
          "id": "ui_v_1",
          "target": "Vino",
          "phonetic": "وینو",
          "native_meaning": "وائن / انگور کا رس",
          "english": "Wine",
          "example_sentence_target": "Il vino è rosso.",
          "example_sentence_native": "وائن سرخ ہے۔",
          "example_sentence_phonetic": "اِل وینو اے روسو۔"
        }
      ],
      "exercises": {
        "writingPractice": [{ "id": "w_ui_v", "letter": "V", "hint": "V لکھیں" }],
        "matching": [{ "id": "m_ui_v", "target": "Vino", "native": "وائن" }]
      },
      "cultural_note": "اٹلی دنیا میں انگور کی کاشت اور وائن کی تیاری میں سرِ فہرست ہے۔",
      "pronunciation_tip": "'V' کا نام 'وو' (Vu) ہے اور آواز 'و' کی ہے۔",
      "progress": { "xp": 50, "streak_bonus": 10, "badge": "IT-V" }
    },
    {
      "week": 3,
      "day": 21,
      "letter": "Z",
      "title": "Day 21: Letter Z",
      "title_native": "اکیسواں دن: حرف Z",
      "theme": "Final Consonant",
      "path": "alphabet",
      "targetLanguage": "Italian",
      "nativeLanguage": "Urdu",
      "words": [
        {
          "id": "ui_z_1",
          "target": "Zucca",
          "phonetic": "تسُوکا",
          "native_meaning": "کدو",
          "english": "Pumpkin",
          "example_sentence_target": "La zucca è gialla.",
          "example_sentence_native": "کدو پیلا ہے۔",
          "example_sentence_phonetic": "لا تسُوکا اے جالا۔"
        }
      ],
      "exercises": {
        "writingPractice": [{ "id": "w_ui_z", "letter": "Z", "hint": "Z لکھیں" }],
        "multipleChoice": [{ "id": "mc_ui_z", "question": "لفظ 'Zucca' میں 'Z' کی آواز کیا ہے؟", "options": ["ز", "تس", "ڈ", "ج"], "correct": 1, "explanation": "اطالوی 'Z' اکثر 'تس' (Ts) کی آواز دیتا ہے۔" }]
      },
      "cultural_note": "کدو اطالوی کھانوں، خاص طور پر پاستا میں بہت استعمال ہوتا ہے۔",
      "pronunciation_tip": "'Z' کا نام 'زیٹا' (Zeta) ہے اور یہ اکثر 'تس' (Ts) جیسی آواز دیتا ہے۔",
      "progress": { "xp": 50, "streak_bonus": 20, "badge": "W3-MASTER" }
    }
  ]
}
