
{
  "week": 1,
  "path": "numbers",
  "targetLanguage": "Hindi",
  "nativeLanguage": "Nepali",
  "days": [
    {
      "week": 1,
      "day": 1,
      "title": "Numbers 0 and 1",
      "title_native": "शून्य र एक (0-1)",
      "theme": "Basics",
      "path": "numbers",
      "targetLanguage": "Hindi",
      "nativeLanguage": "Nepali",
      "words": [
        {
          "id": "nh_n_w1_d1_1",
          "target": "शून्य",
          "phonetic": "शून्य",
          "native_meaning": "शून्य (Zero)",
          "english": "Zero",
          "example_sentence_target": "तापमान शून्य डिग्री है।",
          "example_sentence_native": "तापक्रम शून्य डिग्री छ।",
          "example_sentence_phonetic": "तापमान शून्य डिग्री है।"
        },
        {
          "id": "nh_n_w1_d1_2",
          "target": "एक",
          "phonetic": "एक",
          "native_meaning": "एक (One)",
          "english": "One",
          "example_sentence_target": "मेरे पास एक कलम है।",
          "example_sentence_native": "मसंग एउटा कलम छ।",
          "example_sentence_phonetic": "मेरे पास एक कलम है।"
        }
      ],
      "exercises": {
        "matching": [
          { "id": "nh_n_w1_d1_m1", "target": "शून्य", "native": "०" },
          { "id": "nh_n_w1_d1_m2", "target": "एक", "native": "१" }
        ]
      },
      "cultural_note": "In both Hindi and Nepali, the Devanagari numeral for '1' is written as '१'.",
      "pronunciation_tip": "Hindi 'Ek' is pronounced exactly like the Nepali 'Ek'.",
      "progress": { "xp": 100, "streak_bonus": 10, "badge": "N-W1-D1" }
    },
    {
      "week": 1,
      "day": 2,
      "title": "Numbers 2 and 3",
      "title_native": "दुई र तीन (2-3)",
      "theme": "Basics",
      "path": "numbers",
      "targetLanguage": "Hindi",
      "nativeLanguage": "Nepali",
      "words": [
        {
          "id": "nh_n_w1_d2_1",
          "target": "दो",
          "phonetic": "दो",
          "native_meaning": "दुई (Two)",
          "english": "Two",
          "example_sentence_target": "दो चाय, कृपया।",
          "example_sentence_native": "दुई चिया, कृपया।",
          "example_sentence_phonetic": "दो चाय, कृपया।"
        },
        {
          "id": "nh_n_w1_d2_2",
          "target": "तीन",
          "phonetic": "तीन",
          "native_meaning": "तीन (Three)",
          "english": "Three",
          "example_sentence_target": "तीन दिन बचे हैं।",
          "example_sentence_native": "तीन दिन बाँकी छ।",
          "example_sentence_phonetic": "तीन दिन बचे हैं।"
        }
      ],
      "exercises": {
        "matching": [
          { "id": "nh_n_w1_d2_m1", "target": "दो", "native": "२" },
          { "id": "nh_n_w1_d2_m2", "target": "तीन", "native": "३" }
        ]
      },
      "cultural_note": "The word for 'Two' in Hindi is 'Do', while in Nepali it is 'Dui'.",
      "pronunciation_tip": "Practice the soft 'D' in 'Do'.",
      "progress": { "xp": 100, "streak_bonus": 10, "badge": "N-W1-D2" }
    },
    {
      "week": 1,
      "day": 3,
      "title": "Numbers 4 and 5",
      "title_native": "चार र पाँच (4-5)",
      "theme": "Basics",
      "path": "numbers",
      "targetLanguage": "Hindi",
      "nativeLanguage": "Nepali",
      "words": [
        {
          "id": "nh_n_w1_d3_1",
          "target": "चार",
          "phonetic": "चार",
          "native_meaning": "चार (Four)",
          "english": "Four",
          "example_sentence_target": "चार लोग यहाँ हैं।",
          "example_sentence_native": "चार जना यहाँ छन्।",
          "example_sentence_phonetic": "चार लोग यहाँ हैं।"
        },
        {
          "id": "nh_n_w1_d3_2",
          "target": "पाँच",
          "phonetic": "पाँच",
          "native_meaning": "पाँच (Five)",
          "english": "Five",
          "example_sentence_target": "पाँच रुपये दीजिए।",
          "example_sentence_native": "पाँच रुपैयाँ दिनुहोस्।",
          "example_sentence_phonetic": "पाँच रुपये दीजिए।"
        }
      ],
      "exercises": {
        "matching": [
          { "id": "nh_n_w1_d3_m1", "target": "चार", "native": "४" },
          { "id": "nh_n_w1_d3_m2", "target": "पाँच", "native": "५" }
        ]
      },
      "cultural_note": "These numbers are identical in spelling in both languages.",
      "pronunciation_tip": "The nasal sound in 'Paanch' is important.",
      "progress": { "xp": 100, "streak_bonus": 10, "badge": "N-W1-D3" }
    },
    {
      "week": 1,
      "day": 4,
      "title": "Numbers 6 and 7",
      "title_native": "छ र सात (6-7)",
      "theme": "Basics",
      "path": "numbers",
      "targetLanguage": "Hindi",
      "nativeLanguage": "Nepali",
      "words": [
        {
          "id": "nh_n_w1_d4_1",
          "target": "छह",
          "phonetic": "छ",
          "native_meaning": "छ (Six)",
          "english": "Six",
          "example_sentence_target": "छह बज रहे हैं।",
          "example_sentence_native": "छ बजिरहेको छ।",
          "example_sentence_phonetic": "छह बज रहे हैं।"
        },
        {
          "id": "nh_n_w1_d4_2",
          "target": "सात",
          "phonetic": "सात",
          "native_meaning": "सात (Seven)",
          "english": "Seven",
          "example_sentence_target": "सात समंदर पार।",
          "example_sentence_native": "सात समुद्र पार।",
          "example_sentence_phonetic": "सात समंदर पार।"
        }
      ],
      "exercises": {
        "matching": [
          { "id": "nh_n_w1_d4_m1", "target": "छह", "native": "६" },
          { "id": "nh_n_w1_d4_m2", "target": "सात", "native": "७" }
        ]
      },
      "cultural_note": "Hindi often writes '6' as 'छह' (Chhah) or just 'छ' (Chha).",
      "pronunciation_tip": "The 'H' in 'Chhah' is a very light aspiration.",
      "progress": { "xp": 100, "streak_bonus": 10, "badge": "N-W1-D4" }
    },
    {
      "week": 1,
      "day": 5,
      "title": "Numbers 8 and 9",
      "title_native": "आठ र नौ (8-9)",
      "theme": "Basics",
      "path": "numbers",
      "targetLanguage": "Hindi",
      "nativeLanguage": "Nepali",
      "words": [
        {
          "id": "nh_n_w1_d5_1",
          "target": "आठ",
          "phonetic": "आठ",
          "native_meaning": "आठ (Eight)",
          "english": "Eight",
          "example_sentence_target": "आठ महीने बाद।",
          "example_sentence_native": "आठ महिना पछि।",
          "example_sentence_phonetic": "आठ महीने बाद।"
        },
        {
          "id": "nh_n_w1_d5_2",
          "target": "नौ",
          "phonetic": "नौ",
          "native_meaning": "नौ (Nine)",
          "english": "Nine",
          "example_sentence_target": "नौ बजे मिलते हैं।",
          "example_sentence_native": "नौ बजे भेटौं।",
          "example_sentence_phonetic": "नौ बजे मिलते हैं।"
        }
      ],
      "exercises": {
        "matching": [
          { "id": "nh_n_w1_d5_m1", "target": "आठ", "native": "८" },
          { "id": "nh_n_w1_d5_m2", "target": "नौ", "native": "९" }
        ]
      },
      "cultural_note": "Hindi 'Nau' and Nepali 'Nau' are identical.",
      "pronunciation_tip": "Keep the 'Th' in 'Aath' crisp.",
      "progress": { "xp": 100, "streak_bonus": 10, "badge": "N-W1-D5" }
    },
    {
      "week": 1,
      "day": 6,
      "title": "Number 10",
      "title_native": "दश (10)",
      "theme": "Basics",
      "path": "numbers",
      "targetLanguage": "Hindi",
      "nativeLanguage": "Nepali",
      "words": [
        {
          "id": "nh_n_w1_d6_1",
          "target": "दस",
          "phonetic": "दस",
          "native_meaning": "दश (Ten)",
          "english": "Ten",
          "example_sentence_target": "दस रुपये की चाय।",
          "example_sentence_native": "दश रुपैयाँको चिया।",
          "example_sentence_phonetic": "दस रुपये की चाय।"
        }
      ],
      "exercises": {
        "multipleChoice": [
          {
            "id": "nh_n_w1_d6_q1",
            "question": "What is '१०' in Hindi?",
            "options": ["नौ", "आठ", "दस", "सात"],
            "correct": 2,
            "explanation": "'दस' means Ten."
          }
        ]
      },
      "cultural_note": "Note the spelling difference: Hindi uses 'दस' (S) while Nepali often uses 'दश' (Sh).",
      "pronunciation_tip": "In Hindi, it's a dental 'S' sound.",
      "progress": { "xp": 100, "streak_bonus": 10, "badge": "N-W1-D6" }
    },
    {
      "week": 1,
      "day": 7,
      "title": "Review 0-10",
      "title_native": "पुनरावलोकन (0-10)",
      "theme": "Review",
      "path": "numbers",
      "targetLanguage": "Hindi",
      "nativeLanguage": "Nepali",
      "words": [],
      "exercises": {
        "matching": [
          { "id": "nh_n_w1_d7_m1", "target": "एक", "native": "१" },
          { "id": "nh_n_w1_d7_m2", "target": "दो", "native": "२" },
          { "id": "nh_n_w1_d7_m3", "target": "दस", "native": "१०" },
          { "id": "nh_n_w1_d7_m4", "target": "पाँच", "native": "५" }
        ],
        "sentenceScramble": [
          {
            "id": "nh_n_w1_d7_ss1",
            "scrambled": ["दीजिए", "दस", "रुपये"],
            "correct": "दस रुपये दीजिए",
            "nativeHint": "दश रुपैयाँ दिनुहोस्।"
          }
        ]
      },
      "cultural_note": "Mastering 0-10 is the key to understanding all higher numbers in Hindi.",
      "pronunciation_tip": "Review all sounds from the week.",
      "progress": { "xp": 150, "streak_bonus": 20, "badge": "N-W1-D7" }
    }
  ]
}
