
{
  "week": 4,
  "path": "numbers",
  "targetLanguage": "Arabic",
  "nativeLanguage": "Nepali",
  "days": [
    {
      "week": 4,
      "day": 1,
      "title": "Day 22: Saudi Riyal / UAE Dirham",
      "title_native": "बाह्रौ दिन: साउदी रियाल / यूएई दिराम",
      "theme": "Money",
      "path": "numbers",
      "targetLanguage": "Arabic",
      "nativeLanguage": "Nepali",
      "words": [
        { "id": "n4_1_1", "target": "ريال سُعودي", "phonetic": "रियाल सुउदी", "native_meaning": "साउदी रियाल", "english": "Saudi Riyal" },
        { "id": "n4_1_2", "target": "درهم إماراتي", "phonetic": "दिरहम इमिराती", "native_meaning": "यूएई दिराम", "english": "UAE Dirham" },
        { "id": "n4_1_3", "target": "فلوس / نقود", "phonetic": "फलुस", "native_meaning": "पैसा", "english": "Money" }
      ],
      "exercises": {
        "matching": [
          { "id": "m4_1_1", "target": "ريال", "native": "रियाल" },
          { "id": "m4_1_2", "target": "درهم", "native": "दिराम" }
        ]
      },
      "cultural_note": "पसलमा सामान्यतया पैसालाई 'फलुस' भनिन्छ।",
      "pronunciation_tip": "'फलुस' भन्दा अन्तिममा 'स' स्पष्टसँग भन्नुहोस्।",
      "progress": { "xp": 100, "streak_bonus": 10, "badge": "N4D1-Money" }
    },
    {
      "week": 4,
      "day": 2,
      "title": "Day 23: Asking 'How much?'",
      "title_native": "तेइसौ दिन: 'कति हो?' सोध्ने",
      "theme": "Money",
      "path": "numbers",
      "targetLanguage": "Arabic",
      "nativeLanguage": "Nepali",
      "words": [
        { "id": "n4_2_1", "target": "بكم؟", "phonetic": "बिकम?", "native_meaning": "कति हो? (How much?)", "english": "How much?", "example_sentence_target": "بكم هذا؟", "example_sentence_native": "यसको कति हो?", "example_sentence_phonetic": "बिकम हादा?" },
        { "id": "n4_2_2", "target": "غالي", "phonetic": "गाली", "native_meaning": "महँगो", "english": "Expensive" },
        { "id": "n4_2_3", "target": "رخيص", "phonetic": "रखीस", "native_meaning": "सस्तो", "english": "Cheap" }
      ],
      "exercises": {
        "sentenceScramble": [
          {
            "id": "ss4_2_1",
            "scrambled": ["هذا", "بكم", "؟"],
            "correct": "بكم هذا ؟",
            "nativeHint": "यसको कति हो?"
          }
        ]
      },
      "cultural_note": "अरबी बजारहरूमा मूल्य घटाउनका लागि मोलमोलाइ (Bargaining) गर्ने चलन छ।",
      "pronunciation_tip": "'गाली' मा 'ग' घाँटीको गहिराइबाट 'घ' जस्तै सुनिने गरी भन्नुहोस्।",
      "progress": { "xp": 100, "streak_bonus": 10, "badge": "N4D2-Price" }
    },
    {
      "week": 4,
      "day": 3,
      "title": "Day 24: Telling Time (Hours)",
      "title_native": "चौबिसौ दिन: समय (घण्टा)",
      "theme": "Time",
      "path": "numbers",
      "targetLanguage": "Arabic",
      "nativeLanguage": "Nepali",
      "words": [
        { "id": "n4_3_1", "target": "كم الساعة؟", "phonetic": "कम अल-साआ?", "native_meaning": "कति बज्यो?", "english": "What time is it?", "example_sentence_target": "الساعة الواحدة.", "example_sentence_native": "एक बज्यो।", "example_sentence_phonetic": "अल-साआ अल-वाहिदा।" }
      ],
      "exercises": {
        "matching": [
          { "id": "m4_3_1", "target": "الساعة", "native": "घडी / समय" },
          { "id": "m4_3_2", "target": "الآن", "native": "अहिले" }
        ]
      },
      "cultural_note": "समय सोध्दा 'साआ' शब्द प्रयोग हुन्छ, जसको अर्थ घडी पनि हुन्छ।",
      "pronunciation_tip": "'साआ' को बीचमा हल्का रोकिनुहोस् ताकि दुवै 'आ' स्पष्ट सुनिउन्।",
      "progress": { "xp": 100, "streak_bonus": 10, "badge": "N4D3-Time-Hours" }
    },
    {
      "week": 4,
      "day": 4,
      "title": "Day 25: Half and Quarter",
      "title_native": "पच्चिसौ दिन: आधा र सवा",
      "theme": "Time",
      "path": "numbers",
      "targetLanguage": "Arabic",
      "nativeLanguage": "Nepali",
      "words": [
        { "id": "n4_4_1", "target": "نصف", "phonetic": "निसफ", "native_meaning": "आधा (Half)", "english": "Half", "example_sentence_target": "الساعة واحدة ونصف.", "example_sentence_native": "डेढ बज्यो।", "example_sentence_phonetic": "अल-साआ वाहिदा वा निसफ।" },
        { "id": "n4_4_2", "target": "ربع", "phonetic": "रुबा", "native_meaning": "सवा / पौने (Quarter)", "english": "Quarter" }
      ],
      "exercises": {
        "fillBlanks": [
          { "id": "f4_4_1", "sentence": "डेढ बज्यो भन्नलाई अरबीमा 'वाहिदा वा ___' भनिन्छ।", "answer": "निसफ", "hint": "Ni-sf" }
        ]
      },
      "cultural_note": "अरबीमा समय भन्दा 'र' (Wa) शब्दले दुई भागलाई जोड्छ, जस्तै 'वाहिदा वा निसफ' (एक र आधा)।",
      "progress": { "xp": 100, "streak_bonus": 10, "badge": "N4D4-Time-Fractions" }
    },
    {
      "week": 4,
      "day": 5,
      "title": "Day 26: AM and PM",
      "title_native": "छब्बीसौ दिन: बिहान र बेलुका",
      "theme": "Time",
      "path": "numbers",
      "targetLanguage": "Arabic",
      "nativeLanguage": "Nepali",
      "words": [
        { "id": "n4_5_1", "target": "صباحاً", "phonetic": "सबाहन", "native_meaning": "बिहान (AM)", "english": "In the morning", "example_sentence_target": "الساعة ثمانية صباحاً.", "example_sentence_native": "बिहानको आठ बज्यो।", "example_sentence_phonetic": "अल-साआ थमानिया सबाहन।" },
        { "id": "n4_5_2", "target": "مساءً", "phonetic": "मसान", "native_meaning": "बेलुका (PM)", "english": "In the evening" }
      ],
      "exercises": {
        "matching": [
          { "id": "m4_5_1", "target": "صباحاً", "native": "बिहान" },
          { "id": "m4_5_2", "target": "مساءً", "native": "बेलुका" }
        ]
      },
      "progress": { "xp": 100, "streak_bonus": 10, "badge": "N4D5-AM-PM" }
    },
    {
      "week": 4,
      "day": 6,
      "title": "Day 27: Today and Tomorrow",
      "title_native": "सत्ताइसौ दिन: आज र भोलि",
      "theme": "Time",
      "path": "numbers",
      "targetLanguage": "Arabic",
      "nativeLanguage": "Nepali",
      "words": [
        { "id": "n4_6_1", "target": "اليوم", "phonetic": "अल-यौम", "native_meaning": "आज", "english": "Today" },
        { "id": "n4_6_2", "target": "بكرة / غداً", "phonetic": "बुकरा / गदन", "native_meaning": "भोलि", "english": "Tomorrow", "example_sentence_target": "أراك بكرة.", "example_sentence_native": "भोलि भेटौला।", "example_sentence_phonetic": "अराक बुकरा।" }
      ],
      "exercises": {
        "fillBlanks": [
          { "id": "f4_6_1", "sentence": "भोलिलाई अरबीमा ___ भनिन्छ।", "answer": "बुकरा", "hint": "Bu-kra" }
        ]
      },
      "cultural_note": "खाडी देशहरूमा भोलिलाई 'बुकरा' शब्द धेरै बढी प्रयोग गरिन्छ।",
      "pronunciation_tip": "'गदन' मा 'ग' घाँटीको गहिराइबाट निकाल्नुहोस्।",
      "progress": { "xp": 100, "streak_bonus": 10, "badge": "N4D6-Today-Tomorrow" }
    },
    {
      "week": 4,
      "day": 7,
      "title": "Day 28: Numbers Review",
      "title_native": "अठ्ठाइसौ दिन: नम्बरहरूको पुनरावलोकन",
      "theme": "Final Review",
      "path": "numbers",
      "targetLanguage": "Arabic",
      "nativeLanguage": "Nepali",
      "words": [
        { "id": "n4_7_1", "target": "مراجعة", "phonetic": "मुराजा", "native_meaning": "पुनरावलोकन (Review)", "english": "Review" }
      ],
      "exercises": {
        "matching": [
          { "id": "m4_7_1", "target": "١٠", "native": "अशरा" },
          { "id": "m4_7_2", "target": "١٠٠", "native": "मिआ" },
          { "id": "m4_7_3", "target": "١٠٠٠", "native": "अल्फ" }
        ]
      },
      "cultural_note": "तपाईंले अब अरबीमा मूल्य सोध्न, मिति बुझ्न र समय भन्न सक्नुहुन्छ। यो खाडी देशहरूमा काम गर्न धेरै सहयोगी हुनेछ।",
      "progress": { "xp": 200, "streak_bonus": 30, "badge": "N4-Arabic-Numbers-Platinum" }
    }
  ]
}
